invocate/__init__.py
invocate/core.py
invocate/main.py
invocate-0.2.1.dist-info/licenses/LICENSE
invocate-0.2.1.dist-info/METADATA
invocate-0.2.1.dist-info/WHEEL
invocate-0.2.1.dist-info/entry_points.txt
invocate-0.2.1.dist-info/top_level.txt
invocate-0.2.1.dist-info/RECORD
