Metadata-Version: 2.4
Name: invocate
Version: 0.2.1
Summary: Enhanced Invoke task management with simplified namespacing support
Author-email: Fred McDavid <fred@frameworklabs.us>
License: MIT
Project-URL: Homepage, https://github.com/FredworkLemmas/invocate.git
Project-URL: Repository, https://github.com/FredworkLemmas/invocate.git
Project-URL: Bug Tracker, https://github.com/FredworkLemmas/invocate.git/issues
Keywords: invoke,tasks,automation,cli,namespace
Classifier: Development Status :: 4 - Beta
Classifier: Intended Audience :: Developers
Classifier: License :: OSI Approved :: MIT License
Classifier: Operating System :: OS Independent
Classifier: Programming Language :: Python :: 3
Classifier: Programming Language :: Python :: 3.8
Classifier: Programming Language :: Python :: 3.9
Classifier: Programming Language :: Python :: 3.10
Classifier: Programming Language :: Python :: 3.11
Classifier: Programming Language :: Python :: 3.12
Classifier: Topic :: Software Development :: Libraries :: Python Modules
Classifier: Topic :: System :: Systems Administration
Requires-Python: >=3.8
License-File: LICENSE
Requires-Dist: invoke>=2.0.0
Requires-Dist: attrs>=21.0.0
Provides-Extra: dev
Requires-Dist: pytest>=7.0; extra == "dev"
Requires-Dist: flake8>=5.0; extra == "dev"
Provides-Extra: docs
Requires-Dist: sphinx>=5.0; extra == "docs"
Requires-Dist: sphinx-rtd-theme>=1.0; extra == "docs"
Dynamic: license-file
